daisys/__init__.py
daisys/factory.py
daisys/v1/__init__.py
daisys/v1/speak/__init__.py
daisys/v1/speak/async_client.py
daisys/v1/speak/async_websocket.py
daisys/v1/speak/exceptions.py
daisys/v1/speak/models.py
daisys/v1/speak/sync_client.py
daisys/v1/speak/sync_websocket.py
daisys-1.1.0.dist-info/licenses/LICENSE
daisys-1.1.0.dist-info/METADATA
daisys-1.1.0.dist-info/WHEEL
daisys-1.1.0.dist-info/top_level.txt
daisys-1.1.0.dist-info/RECORD
