Metadata-Version: 2.4
Name: daisys
Version: 1.1.0
Summary: Python SDK for daisys.ai
Author-email: "daisys.ai" <api@daisys.ai>
License: MIT
Project-URL: Homepage, https://github.com/daisys-ai/daisys-api-python
Requires-Python: >=3.10
License-File: LICENSE
Requires-Dist: pydantic>=2
Requires-Dist: httpx>=0.28.1
Provides-Extra: ws
Requires-Dist: httpx-ws>=0.7.1; extra == "ws"
Provides-Extra: dev
Requires-Dist: sphinx>=7.0.0; extra == "dev"
Requires-Dist: furo; extra == "dev"
Requires-Dist: sphinxcontrib-napoleon; extra == "dev"
Dynamic: license-file
